soundaktor64/Laptop_Fan.mp3
soundaktor64/main.py
soundaktor64/silicon.py
soundaktor64/sound.py
soundaktor64-0.1.dist-info/METADATA
soundaktor64-0.1.dist-info/WHEEL
soundaktor64-0.1.dist-info/entry_points.txt
soundaktor64-0.1.dist-info/top_level.txt
soundaktor64-0.1.dist-info/RECORD
