Metadata-Version: 2.1
Name: soundaktor64
Version: 0.1
Summary: Fixes main disadvantage of Macbook Air M1
Home-page: https://gitlab.com/egor3f/soundaktor64
Author: Egor3f
Author-email: ef@efprojects.com
License: UNKNOWN
Project-URL: Bug Tracker, https://gitlab.com/egor3f/soundaktor64/issues
Platform: UNKNOWN
Classifier: Development Status :: 3 - Alpha
Classifier: Programming Language :: Python :: 3
Classifier: License :: OSI Approved :: GNU General Public License v3 (GPLv3)
Classifier: Operating System :: MacOS :: MacOS X
Requires-Python: >=3.6
Requires-Dist: pyobjc
